{
  "imdbId": "tt0080661",
  "title": "Dressed to Kill",
  "sortTitle": "Dressed to Kill (1980)",
  "year": 1980,
  "slug": "dressed-to-kill-1980",
  "releaseDate": "1980-07-25",
  "countries": [
    "United States"
  ],
  "genres": [
    "Crime",
    "Drama",
    "Mystery",
    "Thriller"
  ],
  "directors": [
    {
      "imdbId": "nm0000361",
      "name": "Brian De Palma",
      "sequence": 0,
      "notes": null
    }
  ],
  "performers": [
    {
      "imdbId": "nm0000323",
      "name": "Michael Caine",
      "sequence": 0,
      "roles": [
        "Doctor Robert Elliott"
      ],
      "notes": null
    },
    {
      "imdbId": "nm0001141",
      "name": "Angie Dickinson",
      "sequence": 1,
      "roles": [
        "Kate Miller"
      ],
      "notes": null
    },
    {
      "imdbId": "nm0000262",
      "name": "Nancy Allen",
      "sequence": 2,
      "roles": [
        "Liz Blake"
      ],
      "notes": null
    },
    {
      "imdbId": "nm0330360",
      "name": "Keith Gordon",
      "sequence": 3,
      "roles": [
        "Peter Miller"
      ],
      "notes": null
    },
    {
      "imdbId": "nm0001240",
      "name": "Dennis Franz",
      "sequence": 4,
      "roles": [
        "Detective Marino"
      ],
      "notes": null
    },
    {
      "imdbId": "nm0546868",
      "name": "David Margulies",
      "sequence": 5,
      "roles": [
        "Dr. Levy"
      ],
      "notes": null
    },
    {
      "imdbId": "nm0048644",
      "name": "Ken Baker",
      "sequence": 6,
      "roles": [
        "Warren Lockman"
      ],
      "notes": null
    },
    {
      "imdbId": "nm0166290",
      "name": "Susanna Clemm",
      "sequence": 7,
      "roles": [
        "Betty Luce"
      ],
      "notes": null
    },
    {
      "imdbId": "nm0535933",
      "name": "Brandon Maggart",
      "sequence": 8,
      "roles": [
        "Cleveland Sam"
      ],
      "notes": null
    },
    {
      "imdbId": "nm0171876",
      "name": "Amalie Collier",
      "sequence": 9,
      "roles": [
        "Cleaning Woman"
      ],
      "notes": null
    },
    {
      "imdbId": "nm0202629",
      "name": "Mary Davenport",
      "sequence": 10,
      "roles": [
        "Woman in Restaurant"
      ],
      "notes": null
    },
    {
      "imdbId": "nm0223986",
      "name": "Anneka Di Lorenzo",
      "sequence": 11,
      "roles": [
        "Nurse"
      ],
      "notes": "(as Anneka De Lorenzo)"
    },
    {
      "imdbId": "nm0263107",
      "name": "Norman Evans",
      "sequence": 12,
      "roles": [
        "Ted"
      ],
      "notes": null
    },
    {
      "imdbId": "nm0567571",
      "name": "Robbie L. McDermott",
      "sequence": 13,
      "roles": [
        "Man in Shower"
      ],
      "notes": null
    },
    {
      "imdbId": "nm0709876",
      "name": "Bill Randolph",
      "sequence": 14,
      "roles": [
        "Chase Cabbie"
      ],
      "notes": null
    },
    {
      "imdbId": "nm0642508",
      "name": "Sean O'Rinn",
      "sequence": 15,
      "roles": [
        "Museum Cabbie"
      ],
      "notes": null
    },
    {
      "imdbId": "nm0916568",
      "name": "Fred Weber",
      "sequence": 16,
      "roles": [
        "Mike Miller"
      ],
      "notes": null
    },
    {
      "imdbId": "nm0931638",
      "name": "Samm-Art Williams",
      "sequence": 17,
      "roles": [
        "Subway Cop"
      ],
      "notes": null
    },
    {
      "imdbId": "nm0750703",
      "name": "Robert Lee Rush",
      "sequence": 18,
      "roles": [
        "Hood #1"
      ],
      "notes": null
    },
    {
      "imdbId": "nm0780144",
      "name": "Anthony Boyd Scriven",
      "sequence": 19,
      "roles": [
        "Hood #2"
      ],
      "notes": null
    },
    {
      "imdbId": "nm0568344",
      "name": "Robert McDuffie",
      "sequence": 20,
      "roles": [
        "Hood #3"
      ],
      "notes": null
    },
    {
      "imdbId": "nm0761554",
      "name": "Frederick Sanders",
      "sequence": 21,
      "roles": [
        "Hood #4"
      ],
      "notes": null
    }
  ],
  "writers": [
    {
      "imdbId": "nm0000361",
      "name": "Brian De Palma",
      "sequence": 0,
      "notes": "(written by)"
    }
  ]
}