{
  "imdbId": "tt0097276",
  "title": "Enemies, A Love Story",
  "sortTitle": "Enemies, A Love Story (1989)",
  "year": 1989,
  "slug": "enemies-a-love-story-1989",
  "releaseDate": "1989-12-13",
  "releaseDateNotes": null,
  "countries": [
    "United States"
  ],
  "genres": [
    "Comedy",
    "Drama",
    "Romance"
  ],
  "directors": [
    {
      "imdbId": "nm0005196",
      "name": "Paul Mazursky",
      "sequence": 0,
      "notes": null
    }
  ],
  "performers": [
    {
      "imdbId": "nm0798779",
      "name": "Ron Silver",
      "sequence": 0,
      "roles": [
        "Herman"
      ],
      "notes": null
    },
    {
      "imdbId": "nm0001378",
      "name": "Anjelica Huston",
      "sequence": 1,
      "roles": [
        "Tamara"
      ],
      "notes": null
    },
    {
      "imdbId": "nm0000565",
      "name": "Lena Olin",
      "sequence": 2,
      "roles": [
        "Masha"
      ],
      "notes": null
    },
    {
      "imdbId": "nm0825555",
      "name": "Malgorzata Zajaczkowska",
      "sequence": 3,
      "roles": [
        "Yadwiga"
      ],
      "notes": "(as Margaret Sophie Stein)"
    },
    {
      "imdbId": "nm0454418",
      "name": "Alan King",
      "sequence": 4,
      "roles": [
        "Rabbi Lembeck"
      ],
      "notes": null
    },
    {
      "imdbId": "nm0539652",
      "name": "Judith Malina",
      "sequence": 5,
      "roles": [
        "Masha's Mother"
      ],
      "notes": null
    },
    {
      "imdbId": "nm0439334",
      "name": "Rita Karin",
      "sequence": 6,
      "roles": [
        "Mrs. Schreier"
      ],
      "notes": null
    },
    {
      "imdbId": "nm0498609",
      "name": "Phil Leeds",
      "sequence": 7,
      "roles": [
        "Pesheles"
      ],
      "notes": null
    },
    {
      "imdbId": "nm0059946",
      "name": "Elya Baskin",
      "sequence": 8,
      "roles": [
        "Yasha Kobik"
      ],
      "notes": null
    },
    {
      "imdbId": "nm0005196",
      "name": "Paul Mazursky",
      "sequence": 9,
      "roles": [
        "Leon Tortshiner"
      ],
      "notes": null
    },
    {
      "imdbId": "nm0231170",
      "name": "L.J. Dollinger",
      "sequence": 10,
      "roles": [
        "Reb Nissen Yaroslaver"
      ],
      "notes": null
    },
    {
      "imdbId": "nm0816700",
      "name": "Zypora Spaisman",
      "sequence": 11,
      "roles": [
        "Sheva Haddas"
      ],
      "notes": null
    },
    {
      "imdbId": "nm0343557",
      "name": "Arthur Grosser",
      "sequence": 12,
      "roles": [
        "Doctor"
      ],
      "notes": null
    },
    {
      "imdbId": "nm0509369",
      "name": "Burney Lieberman",
      "sequence": 13,
      "roles": [
        "Yom Kippur Cantor"
      ],
      "notes": null
    },
    {
      "imdbId": "nm0441944",
      "name": "Nathaniel Katzman",
      "sequence": 14,
      "roles": [
        "Wedding Cantor"
      ],
      "notes": null
    },
    {
      "imdbId": "nm0307309",
      "name": "Gayle Garfinkle",
      "sequence": 15,
      "roles": [
        "Mrs. Lembeck"
      ],
      "notes": null
    },
    {
      "imdbId": "nm0326326",
      "name": "Shel Goldstein",
      "sequence": 16,
      "roles": [
        "Mrs. Regal"
      ],
      "notes": "(as Shelley Goldstein)"
    },
    {
      "imdbId": "nm0111391",
      "name": "Henry Bronchtein",
      "sequence": 17,
      "roles": [
        "Benny"
      ],
      "notes": null
    },
    {
      "imdbId": "nm0753447",
      "name": "Howard Ryshpan",
      "sequence": 18,
      "roles": [
        "Onlooker"
      ],
      "notes": null
    },
    {
      "imdbId": "nm0334564",
      "name": "Doris Gramovot",
      "sequence": 19,
      "roles": [
        "Yadwiga's Neighbor"
      ],
      "notes": null
    },
    {
      "imdbId": "nm0589479",
      "name": "Vera Miller",
      "sequence": 20,
      "roles": [
        "Masha's Neighbor"
      ],
      "notes": null
    },
    {
      "imdbId": "nm0043127",
      "name": "Shimon Aviel",
      "sequence": 21,
      "roles": [
        "Windbag"
      ],
      "notes": null
    },
    {
      "imdbId": "nm0338461",
      "name": "Jacob Greenbaum",
      "sequence": 22,
      "roles": [
        "Rabbi at Catskills"
      ],
      "notes": null
    },
    {
      "imdbId": "nm0790949",
      "name": "Rhona Shekter",
      "sequence": 23,
      "roles": [
        "Rabbi's Wife"
      ],
      "notes": null
    },
    {
      "imdbId": "nm0682741",
      "name": "Bobby Pierson",
      "sequence": 24,
      "roles": [
        "Rhumba Instructor"
      ],
      "notes": null
    },
    {
      "imdbId": "nm0781060",
      "name": "Edward Sebic",
      "sequence": 25,
      "roles": [
        "Fitness Instructor"
      ],
      "notes": null
    },
    {
      "imdbId": "nm0581141",
      "name": "Shirley Merovitz",
      "sequence": 26,
      "roles": [
        "Catskill Woman"
      ],
      "notes": null
    },
    {
      "imdbId": "nm0111432",
      "name": "Robin Bronfman",
      "sequence": 27,
      "roles": [
        "Catskill Woman"
      ],
      "notes": null
    },
    {
      "imdbId": "nm0072419",
      "name": "Tyrone Benskin",
      "sequence": 28,
      "roles": [
        "Cabbie"
      ],
      "notes": null
    },
    {
      "imdbId": "nm0084185",
      "name": "Rummy Bishop",
      "sequence": 29,
      "roles": [
        "Waiter at Dairy Restaurant"
      ],
      "notes": null
    },
    {
      "imdbId": "nm0233188",
      "name": "Brian Dooley",
      "sequence": 30,
      "roles": [
        "Man on Ladder"
      ],
      "notes": null
    },
    {
      "imdbId": "nm0271863",
      "name": "Kevin Fenlon",
      "sequence": 31,
      "roles": [
        "Desk Clerk"
      ],
      "notes": null
    },
    {
      "imdbId": "nm0368299",
      "name": "Maral Hassib",
      "sequence": 32,
      "roles": [
        "Hooker"
      ],
      "notes": null
    },
    {
      "imdbId": "nm0654195",
      "name": "Libby Owen",
      "sequence": 33,
      "roles": [
        "Cashier"
      ],
      "notes": null
    },
    {
      "imdbId": "nm0818272",
      "name": "Sam Sperber",
      "sequence": 34,
      "roles": [
        "Violinist"
      ],
      "notes": null
    },
    {
      "imdbId": "nm0133602",
      "name": "Tommy Canary",
      "sequence": 35,
      "roles": [
        "Cotton Candy Man"
      ],
      "notes": null
    },
    {
      "imdbId": "nm0164550",
      "name": "Terry Clark",
      "sequence": 36,
      "roles": [
        "Beach Acrobat"
      ],
      "notes": null
    },
    {
      "imdbId": "nm0731663",
      "name": "Wally Roberts",
      "sequence": 37,
      "roles": [
        "Barker"
      ],
      "notes": null
    },
    {
      "imdbId": "nm0900341",
      "name": "Joe Viviani",
      "sequence": 38,
      "roles": [
        "Newstand Vendor"
      ],
      "notes": null
    },
    {
      "imdbId": "nm0242212",
      "name": "Michael Dunetz",
      "sequence": 39,
      "roles": [
        "Customer"
      ],
      "notes": null
    },
    {
      "imdbId": "nm0611756",
      "name": "Mick Muldoon",
      "sequence": 40,
      "roles": [
        "Doorman"
      ],
      "notes": null
    },
    {
      "imdbId": "nm0501308",
      "name": "Marie-Ad\u00e8le Lemieux",
      "sequence": 41,
      "roles": [
        "Baby Masha"
      ],
      "notes": null
    },
    {
      "imdbId": "nm0003135",
      "name": "Victoria Barkoff",
      "sequence": 42,
      "roles": [
        "Party Goer"
      ],
      "notes": null
    },
    {
      "imdbId": "nm0074197",
      "name": "Harvey Berger",
      "sequence": 43,
      "roles": [
        "Party Goer"
      ],
      "notes": null
    },
    {
      "imdbId": "nm0179121",
      "name": "Arthur Corber",
      "sequence": 44,
      "roles": [
        "Party Goer"
      ],
      "notes": null
    },
    {
      "imdbId": "nm0204084",
      "name": "Carolyn Davine",
      "sequence": 45,
      "roles": [
        "Party Goer"
      ],
      "notes": null
    },
    {
      "imdbId": "nm0231493",
      "name": "Norris Domingue",
      "sequence": 46,
      "roles": [
        "Party Goer"
      ],
      "notes": null
    },
    {
      "imdbId": "nm0384312",
      "name": "Harry Hill",
      "sequence": 47,
      "roles": [
        "Party Goer"
      ],
      "notes": null
    },
    {
      "imdbId": "nm0511613",
      "name": "Ilana Linden",
      "sequence": 48,
      "roles": [
        "Party Goer"
      ],
      "notes": null
    },
    {
      "imdbId": "nm0706017",
      "name": "James Rae",
      "sequence": 49,
      "roles": [
        "Nazi"
      ],
      "notes": null
    },
    {
      "imdbId": "nm0889707",
      "name": "Daniel Varga",
      "sequence": 50,
      "roles": [
        "Nazi"
      ],
      "notes": null
    },
    {
      "imdbId": "nm0147350",
      "name": "Joe Cazalet",
      "sequence": 51,
      "roles": [
        "Nazi"
      ],
      "notes": null
    },
    {
      "imdbId": "nm0830044",
      "name": "Helmut Stiebl",
      "sequence": 52,
      "roles": [
        "Nazi"
      ],
      "notes": null
    },
    {
      "imdbId": "nm0334823",
      "name": "Robert Grande",
      "sequence": 53,
      "roles": [
        "Nazi"
      ],
      "notes": null
    }
  ],
  "writers": [
    {
      "imdbId": "nm0801953",
      "name": "Isaac Bashevis Singer",
      "sequence": 0,
      "notes": "(novel)"
    },
    {
      "imdbId": "nm0800363",
      "name": "Roger L. Simon",
      "sequence": 1,
      "notes": "(screenplay)"
    },
    {
      "imdbId": "nm0005196",
      "name": "Paul Mazursky",
      "sequence": 2,
      "notes": "(screenplay)"
    }
  ]
}