{
  "fetched": "2023-11-29.1",
  "imdbId": "tt0076734",
  "slug": "soldier-of-orange-1977",
  "title": "Soldier of Orange",
  "originalTitle": "Soldaat van Oranje",
  "sortTitle": "Soldier of Orange",
  "year": 1977,
  "releaseDate": "1979-06-22",
  "countries": [
    "Netherlands",
    "Belgium"
  ],
  "genres": [
    "Drama",
    "Romance",
    "Thriller",
    "War"
  ],
  "directors": [
    {
      "imdbId": "nm0000682",
      "name": "Paul Verhoeven",
      "sequence": 0
    }
  ],
  "performers": [
    {
      "imdbId": "nm0000442",
      "name": "Rutger Hauer",
      "sequence": 0,
      "roles": [
        "Erik Lanshof"
      ]
    },
    {
      "imdbId": "nm0469103",
      "name": "Jeroen Krabb\u00e9",
      "sequence": 1,
      "roles": [
        "Guus LeJeune"
      ]
    },
    {
      "imdbId": "nm0671854",
      "name": "Susan Penhaligon",
      "sequence": 2,
      "roles": [
        "Susan"
      ]
    },
    {
      "imdbId": "nm0002081",
      "name": "Edward Fox",
      "sequence": 3,
      "roles": [
        "Colonel Rafelli"
      ]
    },
    {
      "imdbId": "nm0216683",
      "name": "Lex van Delden",
      "sequence": 4,
      "roles": [
        "Nico"
      ]
    },
    {
      "imdbId": "nm0513190",
      "name": "Derek de Lint",
      "sequence": 5,
      "roles": [
        "Alex"
      ]
    },
    {
      "imdbId": "nm0740559",
      "name": "Huib Rooymans",
      "sequence": 6,
      "roles": [
        "Jan Weinberg"
      ]
    },
    {
      "imdbId": "nm0904093",
      "name": "Dolf de Vries",
      "sequence": 7,
      "roles": [
        "Jack Ten Brinck"
      ]
    },
    {
      "imdbId": "nm0352127",
      "name": "Eddy Habbema",
      "sequence": 8,
      "roles": [
        "Robby Froost"
      ]
    },
    {
      "imdbId": "nm0582802",
      "name": "Belinda Meuldijk",
      "sequence": 9,
      "roles": [
        "Esther"
      ]
    },
    {
      "imdbId": "nm0264512",
      "name": "Peter Faber",
      "sequence": 10,
      "roles": [
        "Will Dostgaarde"
      ]
    },
    {
      "imdbId": "nm0329693",
      "name": "Rijk de Gooyer",
      "sequence": 11,
      "roles": [
        "Gestapo-man Breitner"
      ]
    },
    {
      "imdbId": "nm0104597",
      "name": "Paul Brandenburg",
      "sequence": 12,
      "roles": [
        "SS Lt. Thelen"
      ]
    },
    {
      "imdbId": "nm0712417",
      "name": "Ward de Ravet",
      "sequence": 13,
      "roles": [
        "Resistance Leader"
      ]
    },
    {
      "imdbId": "nm0835399",
      "name": "Bert Struys",
      "sequence": 14,
      "roles": [
        "Resistance Leader"
      ]
    },
    {
      "imdbId": "nm0464170",
      "name": "Reinhard Kolldehoff",
      "sequence": 15,
      "roles": [
        "Geisman"
      ]
    },
    {
      "imdbId": "nm0231346",
      "name": "Andrea Domburg",
      "sequence": 16,
      "roles": [
        "Queen Wilhelmina"
      ]
    },
    {
      "imdbId": "nm0379462",
      "name": "Guus Hermus",
      "sequence": 17,
      "roles": [
        "Van der Zanden"
      ]
    },
    {
      "imdbId": "nm0021706",
      "name": "Henny Alma",
      "sequence": 18,
      "roles": [
        "Queen's Secretary"
      ]
    },
    {
      "imdbId": "nm0029177",
      "name": "Bert Andr\u00e9",
      "sequence": 19,
      "roles": [
        "Gekke Dirk"
      ]
    },
    {
      "imdbId": "nm0044681",
      "name": "Cas Baas",
      "sequence": 20,
      "roles": [
        "Dutch General"
      ]
    },
    {
      "imdbId": "nm0066390",
      "name": "Tom van Beek",
      "sequence": 21,
      "roles": [
        "Recruiting Officer"
      ]
    },
    {
      "imdbId": "nm0085106",
      "name": "Han Blaauw",
      "sequence": 22,
      "roles": [
        "Dirk"
      ]
    },
    {
      "imdbId": "nm0094527",
      "name": "Arthur Boni",
      "sequence": 23,
      "roles": [
        "Otto"
      ]
    },
    {
      "imdbId": "nm0112382",
      "name": "Huib Broos",
      "sequence": 24,
      "roles": [
        "April Fools Man"
      ]
    },
    {
      "imdbId": "nm0173860",
      "name": "Jacques Commandeur",
      "sequence": 25,
      "roles": [
        "Prison Cmdr Colonel"
      ]
    },
    {
      "imdbId": "nm0215282",
      "name": "Truus Dekker",
      "sequence": 26,
      "roles": [
        "Mrs. Lanshof"
      ]
    },
    {
      "imdbId": "nm0226650",
      "name": "Bert Dijkstra",
      "sequence": 27,
      "roles": [
        "Milk Man"
      ]
    },
    {
      "imdbId": "nm0887069",
      "name": "Willy Van Heesvelde",
      "sequence": 28,
      "roles": [
        "PT Boat Captain"
      ]
    },
    {
      "imdbId": "nm0374408",
      "name": "Bruni Heinke",
      "sequence": 29,
      "roles": [
        "Party Girl"
      ]
    },
    {
      "imdbId": "nm0377328",
      "name": "Del Henney",
      "sequence": 30,
      "roles": [
        "Sergeant"
      ]
    },
    {
      "imdbId": "nm0498798",
      "name": "Hannah de Leeuwe",
      "sequence": 31,
      "roles": [
        "Party Girl"
      ]
    },
    {
      "imdbId": "nm0496420",
      "name": "John Leddy",
      "sequence": 32,
      "roles": [
        "Resistance Leader"
      ]
    },
    {
      "imdbId": "nm0530582",
      "name": "Bob L\u00f6wenstein",
      "sequence": 33,
      "roles": [
        "Resistance Leader"
      ]
    },
    {
      "imdbId": "nm0418175",
      "name": "Kitty Janssen",
      "sequence": 34,
      "roles": [
        "Greta, Landlady"
      ]
    },
    {
      "imdbId": "nm0465558",
      "name": "Hugo Koolschijn",
      "sequence": 35,
      "roles": [
        "German Navy Officer"
      ]
    },
    {
      "imdbId": "nm0468120",
      "name": "Wim Kouwenhoven",
      "sequence": 36,
      "roles": [
        "Resistance Leader"
      ]
    },
    {
      "imdbId": "nm0576782",
      "name": "Con Meyer",
      "sequence": 37,
      "roles": [
        "Soldier"
      ]
    },
    {
      "imdbId": "nm0583409",
      "name": "Wim de Meijer",
      "sequence": 38,
      "roles": [
        "Alex's Father"
      ]
    },
    {
      "imdbId": "nm0585249",
      "name": "Mary Michon",
      "sequence": 39,
      "roles": [
        "Alex's Mother"
      ]
    },
    {
      "imdbId": "nm0612156",
      "name": "Hero Muller",
      "sequence": 40,
      "roles": [
        "Soldier"
      ]
    },
    {
      "imdbId": "nm0773499",
      "name": "Johan Schmitz",
      "sequence": 41,
      "roles": [
        "Resistance Leader"
      ]
    },
    {
      "imdbId": "nm0781045",
      "name": "Karel Sebesta",
      "sequence": 42,
      "roles": [
        "Soldier"
      ]
    },
    {
      "imdbId": "nm0883542",
      "name": "Serge-Henri Valcke",
      "sequence": 43,
      "roles": [
        "Soldier"
      ]
    },
    {
      "imdbId": "nm0903782",
      "name": "Henk Votel",
      "sequence": 44,
      "roles": [
        "Soldier"
      ]
    }
  ],
  "writers": [
    {
      "imdbId": "nm0736361",
      "name": "Erik Hazelhoff Roelfzema",
      "sequence": 0,
      "notes": "(book \"Soldaat van Oranje '40-'45\")"
    },
    {
      "imdbId": "nm0390537",
      "name": "Kees Holierhoek",
      "sequence": 2,
      "notes": "()"
    },
    {
      "imdbId": "nm0812121",
      "name": "Gerard Soeteman",
      "sequence": 4,
      "notes": "()"
    },
    {
      "imdbId": "nm0000682",
      "name": "Paul Verhoeven",
      "sequence": 6,
      "notes": "()"
    }
  ]
}