{
  "fetched": "2023-11-29.1",
  "imdbId": "tt1430132",
  "slug": "the-wolverine-2013",
  "title": "The Wolverine",
  "originalTitle": "The Wolverine",
  "sortTitle": "Wolverine, The",
  "year": 2013,
  "releaseDate": "2013-07-26",
  "countries": [
    "United States",
    "United Kingdom",
    "Japan"
  ],
  "genres": [
    "Action",
    "Sci-Fi"
  ],
  "directors": [
    {
      "imdbId": "nm0003506",
      "name": "James Mangold",
      "sequence": 0
    }
  ],
  "performers": [
    {
      "imdbId": "nm0413168",
      "name": "Hugh Jackman",
      "sequence": 0,
      "roles": [
        "Logan"
      ]
    },
    {
      "imdbId": "nm5148840",
      "name": "Tao Okamoto",
      "sequence": 1,
      "roles": [
        "Mariko"
      ]
    },
    {
      "imdbId": "nm3822462",
      "name": "Rila Fukushima",
      "sequence": 2,
      "roles": [
        "Yukio"
      ]
    },
    {
      "imdbId": "nm0760796",
      "name": "Hiroyuki Sanada",
      "sequence": 3,
      "roles": [
        "Shingen"
      ]
    },
    {
      "imdbId": "nm1300303",
      "name": "Svetlana Khodchenkova",
      "sequence": 4,
      "roles": [
        "Viper"
      ]
    },
    {
      "imdbId": "nm0974575",
      "name": "Brian Tee",
      "sequence": 5,
      "roles": [
        "Noburo"
      ]
    },
    {
      "imdbId": "nm0945563",
      "name": "Hal Yamanouchi",
      "sequence": 6,
      "roles": [
        "Yashida"
      ]
    },
    {
      "imdbId": "nm0498449",
      "name": "Will Yun Lee",
      "sequence": 7,
      "roles": [
        "Harada"
      ]
    },
    {
      "imdbId": "nm4576636",
      "name": "Ken Yamamura",
      "sequence": 8,
      "roles": [
        "Young Yashida"
      ]
    },
    {
      "imdbId": "nm0000463",
      "name": "Famke Janssen",
      "sequence": 9,
      "roles": [
        "Jean Grey"
      ]
    },
    {
      "imdbId": "nm5810578",
      "name": "Nobutaka Aoyagi",
      "sequence": 10,
      "roles": [
        "Security"
      ]
    },
    {
      "imdbId": "nm5810579",
      "name": "Seiji Funamoto",
      "sequence": 11,
      "roles": [
        "Servant"
      ]
    },
    {
      "imdbId": "nm3758887",
      "name": "Shinji Ikefuji",
      "sequence": 12,
      "roles": [
        "Pock-Face"
      ]
    },
    {
      "imdbId": "nm1903101",
      "name": "Qyoko Kudo",
      "sequence": 13,
      "roles": [
        "Aya"
      ]
    },
    {
      "imdbId": "nm1085711",
      "name": "Nobuaki Kakuda",
      "sequence": 14,
      "roles": [
        "Buddhist Priest"
      ]
    },
    {
      "imdbId": "nm5304363",
      "name": "Chiharu Mizuno",
      "sequence": 15,
      "roles": [
        "Old Woman"
      ]
    },
    {
      "imdbId": "nm3356092",
      "name": "Takao Kinoshita",
      "sequence": 16,
      "roles": [
        "Fruit Cart Vendor"
      ]
    },
    {
      "imdbId": "nm0170865",
      "name": "Conrad Coleby",
      "sequence": 17,
      "roles": [
        "Red Beard"
      ]
    },
    {
      "imdbId": "nm2850355",
      "name": "Taris Tyler",
      "sequence": 18,
      "roles": [
        "Bar Man"
      ]
    },
    {
      "imdbId": "nm5810580",
      "name": "Sarah Naylor-Liddell",
      "sequence": 19,
      "roles": [
        "Yukon Bar Patron"
      ]
    },
    {
      "imdbId": "nm5810581",
      "name": "Joshua Remilton",
      "sequence": 20,
      "roles": [
        "Yukon Bar Patron",
        "Man Near Bar"
      ]
    },
    {
      "imdbId": "nm5810582",
      "name": "Andy Owens",
      "sequence": 21,
      "roles": [
        "Yukon Bar Patron"
      ]
    },
    {
      "imdbId": "nm0691597",
      "name": "Allan Poppleton",
      "sequence": 22,
      "roles": [
        "Yukon Bar Patron"
      ]
    },
    {
      "imdbId": "nm5810583",
      "name": "Geoff Burke",
      "sequence": 23,
      "roles": [
        "Bartender"
      ]
    },
    {
      "imdbId": "nm4938249",
      "name": "Yasuyo Shiba",
      "sequence": 24,
      "roles": [
        "Reporter 1"
      ]
    },
    {
      "imdbId": "nm2608883",
      "name": "Mai Ishikawa",
      "sequence": 25,
      "roles": [
        "Reporter 2"
      ]
    },
    {
      "imdbId": "nm5810585",
      "name": "Yaeko Kimura",
      "sequence": 26,
      "roles": [
        "Mieko"
      ]
    },
    {
      "imdbId": "nm5810586",
      "name": "Ryuta Kimura",
      "sequence": 27,
      "roles": [
        "Hitoshi"
      ]
    },
    {
      "imdbId": "nm2919345",
      "name": "Briden Starr",
      "sequence": 28,
      "roles": [
        "Party Girl 1"
      ]
    },
    {
      "imdbId": "nm5810588",
      "name": "Maria Lukasheva",
      "sequence": 29,
      "roles": [
        "Party Girl 2"
      ]
    },
    {
      "imdbId": "nm3746071",
      "name": "Tess Haubrich",
      "sequence": 30,
      "roles": [
        "Cashier"
      ]
    },
    {
      "imdbId": "nm1794167",
      "name": "Taki Abe",
      "sequence": 31,
      "roles": [
        "Japanese Businessman"
      ]
    },
    {
      "imdbId": "nm5810589",
      "name": "William Takayanagi-Temm",
      "sequence": 32,
      "roles": [
        "Tower Guard"
      ]
    },
    {
      "imdbId": "nm0368058",
      "name": "Kuni Hashimoto",
      "sequence": 33,
      "roles": [
        "Lead Officer"
      ]
    },
    {
      "imdbId": "nm5810590",
      "name": "Chikashi Higaki-Linzbichler",
      "sequence": 34,
      "roles": [
        "Senior Officer at POW Camp"
      ]
    },
    {
      "imdbId": "nm1331443",
      "name": "Shingo Usami",
      "sequence": 35,
      "roles": [
        "Driver"
      ]
    },
    {
      "imdbId": "nm1797212",
      "name": "Naoya Ogawa",
      "sequence": 36,
      "roles": [
        "Yakuza 1"
      ]
    },
    {
      "imdbId": "nm4237590",
      "name": "Atsushi Sawada",
      "sequence": 37,
      "roles": [
        "Yakuza 2"
      ]
    },
    {
      "imdbId": "nm0559690",
      "name": "Takashi Matsuyama",
      "sequence": 38,
      "roles": [
        "Yakuza 3"
      ]
    },
    {
      "imdbId": "nm0945335",
      "name": "Masa Yamaguchi",
      "sequence": 39,
      "roles": [
        "Yakuza 4"
      ]
    },
    {
      "imdbId": "nm2362572",
      "name": "Eric Laciste",
      "sequence": 40,
      "roles": [
        "Yakuza 5"
      ]
    },
    {
      "imdbId": "nm2629022",
      "name": "Hideki Sugiguchi",
      "sequence": 41,
      "roles": [
        "Yakuza 6"
      ]
    },
    {
      "imdbId": "nm0756830",
      "name": "Garret Sato",
      "sequence": 42,
      "roles": [
        "Dying Yakuza"
      ]
    },
    {
      "imdbId": "nm5810591",
      "name": "Kosuke Masano",
      "sequence": 43,
      "roles": [
        "Army Officer 1"
      ]
    },
    {
      "imdbId": "nm5810592",
      "name": "Yoji Tatsuta",
      "sequence": 44,
      "roles": [
        "Army Officer 2"
      ]
    },
    {
      "imdbId": "nm5810593",
      "name": "Yoshinori Fukushige",
      "sequence": 45,
      "roles": [
        "Train Commuter"
      ]
    },
    {
      "imdbId": "nm5810594",
      "name": "Hiroshi Kasuga",
      "sequence": 46,
      "roles": [
        "Yashida Security Guard"
      ]
    },
    {
      "imdbId": "nm5810595",
      "name": "Yumiko Nakamura",
      "sequence": 47,
      "roles": [
        "Mariko Staff"
      ]
    },
    {
      "imdbId": "nm4196048",
      "name": "Kimi",
      "sequence": 48,
      "roles": [
        "Saki"
      ]
    },
    {
      "imdbId": "nm5810596",
      "name": "Keiko Matsumoto",
      "sequence": 49,
      "roles": [
        "Shizu"
      ]
    },
    {
      "imdbId": "nm3810107",
      "name": "Louis Toshio Okada",
      "sequence": 50,
      "roles": [
        "Pat Down Guy"
      ]
    },
    {
      "imdbId": "nm9303576",
      "name": "William Cheung",
      "sequence": 52,
      "roles": [
        "Japanese Businessman",
        "Funeral Guest"
      ]
    },
    {
      "imdbId": "nm6853840",
      "name": "Joe E",
      "sequence": 55,
      "roles": [
        "Funeral Guest",
        "Black Clan Ninja"
      ]
    }
  ],
  "writers": [
    {
      "imdbId": "nm0093560",
      "name": "Mark Bomback",
      "sequence": 0,
      "notes": "(screenplay)"
    },
    {
      "imdbId": "nm0291082",
      "name": "Scott Frank",
      "sequence": 1,
      "notes": "(screenplay)"
    }
  ]
}