{
  "imdbId": "tt0074300",
  "slug": "challenge-of-the-masters-1976",
  "title": "Challenge of the Masters",
  "originalTitle": "Liu A-Cai yu Huang Fei-Hong",
  "sortTitle": "challenge-of-the-masters-1976",
  "year": "1976",
  "releaseDate": "1976-05-07",
  "countries": [
    "Hong Kong"
  ],
  "genres": [
    "Action",
    "Drama"
  ],
  "directors": [
    {
      "imdbId": "nm0514906",
      "name": "Chia-Liang Liu"
    }
  ],
  "performers": [
    {
      "imdbId": "nm0514904",
      "name": "Chia-Hui Liu",
      "roles": [
        "Huang Fei Hung"
      ]
    },
    {
      "imdbId": "nm0155291",
      "name": "Chen Kuan-Tai",
      "roles": [
        "Lu Ah Tsai"
      ],
      "notes": "(as Kuan Tai Chen)"
    },
    {
      "imdbId": "nm0399070",
      "name": "Yue Wong",
      "roles": [
        "Master Lin Tu-chiang"
      ]
    },
    {
      "imdbId": "nm0497763",
      "name": "Lily Li",
      "roles": [
        "Ho Hsiu-lien"
      ]
    },
    {
      "imdbId": "nm0514906",
      "name": "Chia-Liang Liu",
      "roles": [
        "Chen Erh-fu"
      ]
    },
    {
      "imdbId": "nm0156984",
      "name": "Yang Chiang",
      "roles": [
        "Huang Chi-ying"
      ]
    },
    {
      "imdbId": "nm1142885",
      "name": "Chung-Tien Shih",
      "roles": [
        "Master Pang Yun-kang"
      ]
    },
    {
      "imdbId": "nm0514905",
      "name": "Liu Chia-Yung",
      "roles": [
        "Yuen Ching"
      ],
      "notes": "(as Chia-Yung Liu)"
    },
    {
      "imdbId": "nm0465062",
      "name": "Tao Chiang",
      "roles": [
        "Kuo Jen-liang"
      ]
    },
    {
      "imdbId": "nm0155572",
      "name": "Kang-Yeh Cheng",
      "roles": [
        "Tseng Hsing"
      ]
    },
    {
      "imdbId": "nm0025546",
      "name": "Fung Hak-On",
      "roles": [
        "Yang Chung"
      ],
      "notes": "(as Ko-An Fung)"
    },
    {
      "imdbId": "nm2740823",
      "name": "Ho Bao-Hsing",
      "roles": [],
      "notes": "(as Bao-Hsing Ho)"
    },
    {
      "imdbId": "nm0150807",
      "name": "Billy Chan",
      "roles": [
        "Master Pang's Student"
      ]
    },
    {
      "imdbId": "nm1507745",
      "name": "Dik-Hak Chan",
      "roles": [],
      "notes": "(as Ti-Ko Chen)"
    },
    {
      "imdbId": "nm0151005",
      "name": "Lung Chan",
      "roles": [
        "Master Pang's Student"
      ]
    },
    {
      "imdbId": "nm4740363",
      "name": "Ming-Wai Chan",
      "roles": [],
      "notes": "(as Ming-Wei Chen)"
    },
    {
      "imdbId": "nm1747431",
      "name": "Chok-Chow Cheung",
      "roles": [
        "Police Constable"
      ]
    },
    {
      "imdbId": "nm0155578",
      "name": "John Cheung",
      "roles": []
    },
    {
      "imdbId": "nm3082237",
      "name": "Tien-Chu Chin",
      "roles": [
        "Extra"
      ]
    },
    {
      "imdbId": "nm0157304",
      "name": "Yuet-Sang Chin",
      "roles": [
        "Master Lin's Student"
      ]
    },
    {
      "imdbId": "nm0436324",
      "name": "Kam Kong Chow",
      "roles": [
        "Master Pang's Student"
      ]
    },
    {
      "imdbId": "nm0159519",
      "name": "Yun-Kin Chow",
      "roles": [
        "Master Lin's Student"
      ]
    },
    {
      "imdbId": "nm0266762",
      "name": "Yuen Fang",
      "roles": [
        "Extra"
      ]
    },
    {
      "imdbId": "nm0398987",
      "name": "Huang Ha",
      "roles": [
        "Master Lin's Student"
      ],
      "notes": "(as Ha Huang)"
    },
    {
      "imdbId": "nm2410122",
      "name": "Chi-Chang Ho",
      "roles": []
    },
    {
      "imdbId": "nm3063563",
      "name": "Chih-Kuang Huang",
      "roles": [
        "Master Lin's Student"
      ]
    },
    {
      "imdbId": "nm2034575",
      "name": "Pa-Ching Huang",
      "roles": [
        "Uncle Cheng"
      ]
    },
    {
      "imdbId": "nm0401204",
      "name": "Ricky Hui",
      "roles": [
        "Ah Lung"
      ],
      "notes": "(as Kuan-Ying Hsu)"
    },
    {
      "imdbId": "nm2071387",
      "name": "Jen Kwan",
      "roles": [
        "Villager"
      ]
    },
    {
      "imdbId": "nm0482580",
      "name": "Ching-Ying Lam",
      "roles": [
        "Master Pang's Student"
      ]
    },
    {
      "imdbId": "nm0497005",
      "name": "Chiu Lee",
      "roles": [
        "Extra"
      ]
    },
    {
      "imdbId": "nm0444343",
      "name": "Sau-Kei Lee",
      "roles": [
        "Village Elder"
      ]
    },
    {
      "imdbId": "nm0508489",
      "name": "Peng-Fei Li",
      "roles": [
        "Village Elder"
      ]
    },
    {
      "imdbId": "nm0473326",
      "name": "Ke-Ming Lin",
      "roles": []
    },
    {
      "imdbId": "nm1269214",
      "name": "Tze Lin",
      "roles": [
        "Extra"
      ],
      "notes": "(as Lin Tsai)"
    },
    {
      "imdbId": "nm1675222",
      "name": "Yuen Lin",
      "roles": [
        "Villager"
      ]
    },
    {
      "imdbId": "nm0492325",
      "name": "Chiang Lo",
      "roles": []
    },
    {
      "imdbId": "nm0388367",
      "name": "Hoi Mang",
      "roles": [
        "Contestant at Pao Contest"
      ],
      "notes": "(as Hai Meng)"
    },
    {
      "imdbId": "nm2521818",
      "name": "Min Min",
      "roles": []
    },
    {
      "imdbId": "nm1794908",
      "name": "Chik Ngai-Hung",
      "roles": [],
      "notes": "(as Yi-Hsiung Chi)"
    },
    {
      "imdbId": "nm1714999",
      "name": "Gwa-Pau Sai",
      "roles": [
        "Villager"
      ]
    },
    {
      "imdbId": "nm0796185",
      "name": "Hsin Shen",
      "roles": [
        "Extra"
      ]
    },
    {
      "imdbId": "nm0487372",
      "name": "Lao Shen",
      "roles": [
        "Village Elder"
      ]
    },
    {
      "imdbId": "nm1845295",
      "name": "Hsu Sung-Hao",
      "roles": [
        "Master Lin's Student"
      ],
      "notes": "(as Sung-Hao Hsu)"
    },
    {
      "imdbId": "nm2501977",
      "name": "Tung Ting",
      "roles": [
        "Contestant at Pao Contest"
      ]
    },
    {
      "imdbId": "nm0867268",
      "name": "Wilson Tong",
      "roles": [
        "Master Tang"
      ]
    },
    {
      "imdbId": "nm0874676",
      "name": "Eric Tsang",
      "roles": [
        "Master Lin's Student"
      ]
    },
    {
      "imdbId": "nm2387260",
      "name": "Tsai-Pao Tung",
      "roles": [
        "Master Pang's Student"
      ]
    },
    {
      "imdbId": "nm0939327",
      "name": "Shu-Tong Wong",
      "roles": [
        "Extra"
      ],
      "notes": "(as Shu-Tang Huang)"
    },
    {
      "imdbId": "nm0950707",
      "name": "Biao Yuen",
      "roles": [
        "Master Pang's Student"
      ]
    }
  ],
  "writers": [
    {
      "imdbId": "nm0393250",
      "name": "Kuang Ni",
      "notes": "screenplay"
    }
  ],
  "runtimeMinutes": 97,
  "releaseDateCountry": "Hong Kong"
}