{
  "imdbId": "tt1386697",
  "slug": "suicide-squad-2016",
  "title": "Suicide Squad",
  "originalTitle": "Suicide Squad",
  "sortTitle": "Suicide Squad",
  "year": 2016,
  "releaseDate": "2016-08-05",
  "countries": [
    "United States"
  ],
  "genres": [
    "Action",
    "Adventure",
    "Fantasy",
    "Sci-Fi"
  ],
  "directors": [
    {
      "imdbId": "nm0043742",
      "name": "David Ayer",
      "sequence": 0
    }
  ],
  "performers": [
    {
      "imdbId": "nm0000226",
      "name": "Will Smith",
      "sequence": 0,
      "roles": [
        "Deadshot"
      ]
    },
    {
      "imdbId": "nm2968738",
      "name": "Jaime FitzSimons",
      "sequence": 1,
      "roles": [
        "Sergeant Ames Bravo 14"
      ]
    },
    {
      "imdbId": "nm0054697",
      "name": "Ike Barinholtz",
      "sequence": 2,
      "roles": [
        "Griggs"
      ]
    },
    {
      "imdbId": "nm3053338",
      "name": "Margot Robbie",
      "sequence": 3,
      "roles": [
        "Harley Quinn"
      ]
    },
    {
      "imdbId": "nm0246024",
      "name": "Christopher Dyson",
      "sequence": 4,
      "roles": [
        "Missing Hand Guard"
      ]
    },
    {
      "imdbId": "nm2262926",
      "name": "Bambadjan Bamba",
      "sequence": 5,
      "roles": [
        "T-Shirt Vendor"
      ]
    },
    {
      "imdbId": "nm0205626",
      "name": "Viola Davis",
      "sequence": 6,
      "roles": [
        "Amanda Waller"
      ]
    },
    {
      "imdbId": "nm0926471",
      "name": "Ted Whittall",
      "sequence": 7,
      "roles": [
        "Admiral Olsen"
      ]
    },
    {
      "imdbId": "nm1092086",
      "name": "David Harbour",
      "sequence": 8,
      "roles": [
        "Dexter Tolliver"
      ]
    },
    {
      "imdbId": "nm0235960",
      "name": "Robin Atkin Downes",
      "sequence": 9,
      "roles": [
        "Angelo"
      ]
    },
    {
      "imdbId": "nm0448302",
      "name": "Robert B. Kennedy",
      "sequence": 10,
      "roles": [
        "U.S. Marshal"
      ]
    },
    {
      "imdbId": "nm0652893",
      "name": "Billy Otis",
      "sequence": 11,
      "roles": [
        "Mafia Snitch"
      ]
    },
    {
      "imdbId": "nm5666795",
      "name": "Shailyn Pierre-Dixon",
      "sequence": 12,
      "roles": [
        "Zoe"
      ]
    },
    {
      "imdbId": "nm0001467",
      "name": "Jared Leto",
      "sequence": 13,
      "roles": [
        "The Joker"
      ]
    },
    {
      "imdbId": "nm0569651",
      "name": "James McGowan",
      "sequence": 14,
      "roles": [
        "Panda Man"
      ]
    },
    {
      "imdbId": "nm1747924",
      "name": "Jim Parrack",
      "sequence": 15,
      "roles": [
        "Frost"
      ]
    },
    {
      "imdbId": "nm5770636",
      "name": "Derek Perks",
      "sequence": 16,
      "roles": [
        "Psych Patient"
      ]
    },
    {
      "imdbId": "nm0996669",
      "name": "Common",
      "sequence": 17,
      "roles": [
        "Monster T"
      ]
    },
    {
      "imdbId": "nm2541974",
      "name": "Jai Courtney",
      "sequence": 18,
      "roles": [
        "Boomerang"
      ]
    },
    {
      "imdbId": "nm3009232",
      "name": "Ezra Miller",
      "sequence": 19,
      "roles": [
        "The Flash"
      ]
    },
    {
      "imdbId": "nm0379596",
      "name": "Jay Hernandez",
      "sequence": 20,
      "roles": [
        "Diablo"
      ]
    },
    {
      "imdbId": "nm0015382",
      "name": "Adewale Akinnuoye-Agbaje",
      "sequence": 21,
      "roles": [
        "Killer Croc"
      ]
    },
    {
      "imdbId": "nm5353321",
      "name": "Cara Delevingne",
      "sequence": 22,
      "roles": [
        "June Moone",
        "Enchantress"
      ]
    },
    {
      "imdbId": "nm1172478",
      "name": "Joel Kinnaman",
      "sequence": 23,
      "roles": [
        "Rick Flag"
      ]
    },
    {
      "imdbId": "nm0222593",
      "name": "Aidan Devine",
      "sequence": 24,
      "roles": [
        "Chairman"
      ]
    },
    {
      "imdbId": "nm5475583",
      "name": "Andrew Bee",
      "sequence": 25,
      "roles": [
        "Navy One-Star Admiral"
      ]
    },
    {
      "imdbId": "nm8319608",
      "name": "Clive McLean",
      "sequence": 26,
      "roles": [
        "Air Force Two-Star General"
      ]
    },
    {
      "imdbId": "nm3395420",
      "name": "Frank J. Zupancic",
      "sequence": 27,
      "roles": [
        "Army One-Star General"
      ]
    },
    {
      "imdbId": "nm0792199",
      "name": "Kent Sheridan",
      "sequence": 28,
      "roles": [
        "National Security Council"
      ]
    },
    {
      "imdbId": "nm0788141",
      "name": "Roger Shank",
      "sequence": 29,
      "roles": [
        "National Security Council"
      ]
    },
    {
      "imdbId": "nm1495124",
      "name": "Dwight Ireland",
      "sequence": 30,
      "roles": [
        "National Security Council"
      ]
    },
    {
      "imdbId": "nm0115760",
      "name": "Amanda Brugel",
      "sequence": 31,
      "roles": [
        "National Security Council"
      ]
    },
    {
      "imdbId": "nm0448374",
      "name": "Peter Tufford Kennedy",
      "sequence": 32,
      "roles": [
        "National Security Council"
      ]
    },
    {
      "imdbId": "nm6326374",
      "name": "Rosemary De Los Santos",
      "sequence": 33,
      "roles": [
        "Hot Girl Patron"
      ]
    },
    {
      "imdbId": "nm0359322",
      "name": "Kevin Hanchard",
      "sequence": 34,
      "roles": [
        "Casino Boss"
      ]
    },
    {
      "imdbId": "nm1736171",
      "name": "Akotene Chanoine",
      "sequence": 35,
      "roles": [
        "Businessman",
        "Incubus"
      ]
    },
    {
      "imdbId": "nm3389094",
      "name": "Joel Lacoursiere",
      "sequence": 36,
      "roles": [
        "Cop At Rail Terminal"
      ]
    },
    {
      "imdbId": "nm3594614",
      "name": "Jameson Kraemer",
      "sequence": 37,
      "roles": [
        "Doctor At Rail Terminal"
      ]
    },
    {
      "imdbId": "nm0159456",
      "name": "Ho Chow",
      "sequence": 38,
      "roles": [
        "Gate Guard"
      ]
    },
    {
      "imdbId": "nm0052925",
      "name": "Matt Baram",
      "sequence": 39,
      "roles": [
        "Dr. Van Criss"
      ]
    },
    {
      "imdbId": "nm1561803",
      "name": "Birgitte Solem",
      "sequence": 40,
      "roles": [
        "Dr. Van Criss' Wife"
      ]
    },
    {
      "imdbId": "nm2207222",
      "name": "Scott Eastwood",
      "sequence": 41,
      "roles": [
        "Lieutenant GQ Edwards"
      ]
    },
    {
      "imdbId": "nm5244059",
      "name": "Kevin Vance",
      "sequence": 42,
      "roles": [
        "Kowalski - Seal Team A"
      ]
    },
    {
      "imdbId": "nm2158803",
      "name": "Alex Meraz",
      "sequence": 43,
      "roles": [
        "Gomez - Seal Team A"
      ]
    },
    {
      "imdbId": "nm0340703",
      "name": "Tyler Grey",
      "sequence": 44,
      "roles": [
        "Grey - Seal Team Member"
      ]
    },
    {
      "imdbId": "nm0063440",
      "name": "Adam Beach",
      "sequence": 45,
      "roles": [
        "Slipknot"
      ]
    },
    {
      "imdbId": "nm8319609",
      "name": "Nathan Brown",
      "sequence": 46,
      "roles": [
        "Seal Team A #1 Member"
      ]
    },
    {
      "imdbId": "nm7232332",
      "name": "Karen Fukuhara",
      "sequence": 47,
      "roles": [
        "Katana"
      ]
    },
    {
      "imdbId": "nm0158846",
      "name": "Kenneth Choi",
      "sequence": 48,
      "roles": [
        "Yakuza Boss"
      ]
    },
    {
      "imdbId": "nm0885807",
      "name": "Nicolas Van Burek",
      "sequence": 49,
      "roles": [
        "Technician"
      ]
    },
    {
      "imdbId": "nm7487936",
      "name": "Agueda Cardenas",
      "sequence": 50,
      "roles": [
        "Technician 2"
      ]
    },
    {
      "imdbId": "nm3860877",
      "name": "Corina Calderon",
      "sequence": 51,
      "roles": [
        "Grace - Diablo's Wife"
      ]
    },
    {
      "imdbId": "nm8319610",
      "name": "Daniela Uruena",
      "sequence": 52,
      "roles": [
        "Diablo's Daughter"
      ]
    },
    {
      "imdbId": "nm8319611",
      "name": "Nicolas Uruena",
      "sequence": 53,
      "roles": [
        "Diablo's Son"
      ]
    },
    {
      "imdbId": "nm0000255",
      "name": "Ben Affleck",
      "sequence": 54,
      "roles": [
        "Bruce Wayne",
        "Batman"
      ]
    },
    {
      "imdbId": "nm6804482",
      "name": "Shane Clinton Jarvis",
      "sequence": 85,
      "roles": [
        "US Marshal",
        "Military Escort"
      ]
    }
  ],
  "writers": [
    {
      "imdbId": "nm0043742",
      "name": "David Ayer",
      "sequence": 0,
      "notes": "(written by)"
    }
  ],
  "runtimeMinutes": 123,
  "imdbRating": 5.9,
  "imdbVotes": 711870
}