{
  "imdbId": "tt0061080",
  "slug": "texas-across-the-river-1966",
  "title": "Texas Across the River",
  "originalTitle": "Texas Across the River",
  "sortTitle": "texas-across-the-river-1966",
  "year": "1966",
  "releaseDate": "1966-11-28",
  "countries": [
    "United States"
  ],
  "genres": [
    "Comedy",
    "Western"
  ],
  "directors": [
    {
      "imdbId": "nm0330456",
      "name": "Michael Gordon"
    }
  ],
  "performers": [
    {
      "imdbId": "nm0001509",
      "name": "Dean Martin",
      "roles": [
        "Sam Hollis"
      ]
    },
    {
      "imdbId": "nm0001128",
      "name": "Alain Delon",
      "roles": [
        "Don Andrea Baldasar"
      ]
    },
    {
      "imdbId": "nm0287071",
      "name": "Rosemary Forsyth",
      "roles": [
        "Phoebe Ann Naylor"
      ]
    },
    {
      "imdbId": "nm0084086",
      "name": "Joey Bishop",
      "roles": [
        "Kronk"
      ]
    },
    {
      "imdbId": "nm0042106",
      "name": "Tina Aumont",
      "roles": [
        "Lonetta"
      ],
      "notes": "(as Tina Marquand)"
    },
    {
      "imdbId": "nm0336335",
      "name": "Peter Graves",
      "roles": [
        "Capt. Rodney Stimpson"
      ]
    },
    {
      "imdbId": "nm0030516",
      "name": "Michael Ansara",
      "roles": [
        "Iron Jacket"
      ]
    },
    {
      "imdbId": "nm0157607",
      "name": "Linden Chiles",
      "roles": [
        "Yellow Knife"
      ]
    },
    {
      "imdbId": "nm0697785",
      "name": "Andrew Prine",
      "roles": [
        "Lt. Sibley"
      ]
    },
    {
      "imdbId": "nm0027478",
      "name": "Stuart Anderson",
      "roles": [
        "Yancy Cottle"
      ]
    },
    {
      "imdbId": "nm0054117",
      "name": "Roy Barcroft",
      "roles": [
        "Morton"
      ]
    },
    {
      "imdbId": "nm0908647",
      "name": "George D. Wallace",
      "roles": [
        "Willet"
      ],
      "notes": "(as George Wallace)"
    },
    {
      "imdbId": "nm0065975",
      "name": "Don Beddoe",
      "roles": [
        "Mr. Naylor"
      ]
    },
    {
      "imdbId": "nm0861200",
      "name": "Kelly Thordsen",
      "roles": [
        "Jed"
      ]
    },
    {
      "imdbId": "nm0549313",
      "name": "Nora Marlowe",
      "roles": [
        "Emma"
      ]
    },
    {
      "imdbId": "nm0363515",
      "name": "John Harmon",
      "roles": [
        "Gabe"
      ]
    },
    {
      "imdbId": "nm0002070",
      "name": "Richard Farnsworth",
      "roles": [
        "Medicine Man"
      ],
      "notes": "(as Dick Farnsworth)"
    }
  ],
  "writers": [
    {
      "imdbId": "nm0740537",
      "name": "Wells Root",
      "notes": "written by &"
    },
    {
      "imdbId": "nm0338770",
      "name": "Harold Greene",
      "notes": "written by and"
    },
    {
      "imdbId": "nm0823465",
      "name": "Ben Starr",
      "notes": "written by"
    },
    {
      "imdbId": "nm0310775",
      "name": "John Gay",
      "notes": "screenplay collaborator (uncredited)"
    }
  ],
  "runtimeMinutes": 101,
  "releaseDateCountry": "Sweden"
}