{
  "imdbId": "tt0046675",
  "slug": "wuthering-heights-1954",
  "title": "Wuthering Heights",
  "originalTitle": "Abismos de pasión",
  "sortTitle": "Wuthering Heights (1954)",
  "year": "1954",
  "releaseDate": "1954-??-??",
  "countries": [
    "Mexico"
  ],
  "genres": [
    "Drama",
    "Romance"
  ],
  "directors": [
    {
      "imdbId": "nm0000320",
      "name": "Luis Buñuel"
    }
  ],
  "performers": [
    {
      "imdbId": "nm0226773",
      "name": "Irasema Dilián",
      "roles": [
        "Catalina"
      ]
    },
    {
      "imdbId": "nm0592978",
      "name": "Jorge Mistral",
      "roles": [
        "Alejandro"
      ]
    },
    {
      "imdbId": "nm0695033",
      "name": "Lilia Prado",
      "roles": [
        "Isabel"
      ]
    },
    {
      "imdbId": "nm0022172",
      "name": "Ernesto Alonso",
      "roles": [
        "Eduardo"
      ]
    },
    {
      "imdbId": "nm0717592",
      "name": "Francisco Reiguera",
      "roles": [
        "José"
      ]
    },
    {
      "imdbId": "nm0764326",
      "name": "Hortensia Santoveña",
      "roles": [
        "María"
      ]
    },
    {
      "imdbId": "nm0327980",
      "name": "Jaime González Quiñones",
      "roles": [
        "Jorge"
      ]
    },
    {
      "imdbId": "nm0009735",
      "name": "Luis Aceves Castañeda",
      "roles": [
        "Ricardo"
      ]
    }
  ],
  "writers": [
    {
      "imdbId": "nm0111577",
      "name": "Emily Brontë",
      "notes": "(novel \"Wuthering Heights\")"
    },
    {
      "imdbId": "nm0000320",
      "name": "Luis Buñuel",
      "notes": "(story)"
    },
    {
      "imdbId": "nm0000320",
      "name": "Luis Buñuel",
      "notes": "(adaptation)"
    },
    {
      "imdbId": "nm0017855",
      "name": "Julio Alejandro",
      "notes": "(adaptation)"
    },
    {
      "imdbId": "nm0537985",
      "name": "Dino Maiuri",
      "notes": "(adaptation)"
    }
  ],
  "runtimeMinutes": 91,
  "imdbRating": 6.7,
  "imdbVotes": 1371
}