{
  "imdb_id": "tt0068003",
  "sort_title": "King Eagle (1971)",
  "directors": [
    {
      "person_imdb_id": "nm0151653",
      "name": "Cheh Chang",
      "sequence": 0,
      "notes": ""
    }
  ],
  "cast": [
    {
      "person_imdb_id": "nm1036654",
      "name": "Ching Lee",
      "sequence": 0,
      "roles": [
        "An Lu-lien",
        "An Ping-e"
      ],
      "notes": ""
    },
    {
      "person_imdb_id": "nm0862479",
      "name": "Lung Ti",
      "sequence": 1,
      "roles": [
        "Chin Fei"
      ],
      "notes": "(King Eagle)"
    },
    {
      "person_imdb_id": "nm0583955",
      "name": "Miao Ching",
      "sequence": 2,
      "roles": [
        "Wen Hao-pa"
      ],
      "notes": ""
    },
    {
      "person_imdb_id": "nm1083237",
      "name": "Pei-Shan Chang",
      "sequence": 3,
      "roles": [
        "Hung Ching-tien"
      ],
      "notes": ""
    },
    {
      "person_imdb_id": "nm0150991",
      "name": "Lau Chan",
      "sequence": 4,
      "roles": [],
      "notes": ""
    },
    {
      "person_imdb_id": "nm0156449",
      "name": "Chi-Ping Chang",
      "sequence": 5,
      "roles": [],
      "notes": ""
    },
    {
      "person_imdb_id": "nm2964010",
      "name": "Shih-Ou Chang",
      "sequence": 6,
      "roles": [],
      "notes": ""
    },
    {
      "person_imdb_id": "nm0150839",
      "name": "Chuan Chen",
      "sequence": 7,
      "roles": [],
      "notes": ""
    },
    {
      "person_imdb_id": "nm7104456",
      "name": "Hsing Chen",
      "sequence": 8,
      "roles": [
        "Chen Tang"
      ],
      "notes": ""
    },
    {
      "person_imdb_id": "nm2681519",
      "name": "Shao-Chia Chen",
      "sequence": 9,
      "roles": [],
      "notes": ""
    },
    {
      "person_imdb_id": "nm0155594",
      "name": "Lei Cheng",
      "sequence": 10,
      "roles": [],
      "notes": ""
    },
    {
      "person_imdb_id": "nm1794908",
      "name": "Yi-Hsiung Chi",
      "sequence": 11,
      "roles": [],
      "notes": ""
    },
    {
      "person_imdb_id": "nm1095832",
      "name": "Chun Chin",
      "sequence": 12,
      "roles": [],
      "notes": ""
    },
    {
      "person_imdb_id": "nm3082237",
      "name": "Tien-Chu Chin",
      "sequence": 13,
      "roles": [],
      "notes": ""
    },
    {
      "person_imdb_id": "nm0159519",
      "name": "Yun-Kin Chow",
      "sequence": 14,
      "roles": [],
      "notes": ""
    },
    {
      "person_imdb_id": "nm2418542",
      "name": "Chin Chu",
      "sequence": 15,
      "roles": [],
      "notes": ""
    },
    {
      "person_imdb_id": "nm2389486",
      "name": "Chun Erh",
      "sequence": 16,
      "roles": [],
      "notes": ""
    },
    {
      "person_imdb_id": "nm2524036",
      "name": "Yen Fu",
      "sequence": 17,
      "roles": [],
      "notes": ""
    },
    {
      "person_imdb_id": "nm0025546",
      "name": "Hark-On Fung",
      "sequence": 18,
      "roles": [],
      "notes": ""
    },
    {
      "person_imdb_id": "nm4183765",
      "name": "Hsieh-Su Fung",
      "sequence": 19,
      "roles": [],
      "notes": ""
    },
    {
      "person_imdb_id": "nm2740823",
      "name": "Bao-Hsing Ho",
      "sequence": 20,
      "roles": [],
      "notes": ""
    },
    {
      "person_imdb_id": "nm0387360",
      "name": "Pak-Kwong Ho",
      "sequence": 21,
      "roles": [],
      "notes": ""
    },
    {
      "person_imdb_id": "nm0398824",
      "name": "Hsia Hsu",
      "sequence": 22,
      "roles": [],
      "notes": ""
    },
    {
      "person_imdb_id": "nm0398987",
      "name": "Ha Huang",
      "sequence": 23,
      "roles": [],
      "notes": ""
    },
    {
      "person_imdb_id": "nm0399031",
      "name": "Pei-Chi Huang",
      "sequence": 24,
      "roles": [],
      "notes": ""
    },
    {
      "person_imdb_id": "nm1268847",
      "name": "Liu Hung",
      "sequence": 25,
      "roles": [
        "Kao Chen"
      ],
      "notes": ""
    },
    {
      "person_imdb_id": "nm2375628",
      "name": "Hsiung Kao",
      "sequence": 26,
      "roles": [],
      "notes": ""
    },
    {
      "person_imdb_id": "nm4237798",
      "name": "En Lai",
      "sequence": 27,
      "roles": [],
      "notes": ""
    },
    {
      "person_imdb_id": "nm1559536",
      "name": "Wei-Lieh Lan",
      "sequence": 28,
      "roles": [],
      "notes": ""
    },
    {
      "person_imdb_id": "nm0514960",
      "name": "Chun-Fai Lau",
      "sequence": 29,
      "roles": [],
      "notes": ""
    },
    {
      "person_imdb_id": "nm0497005",
      "name": "Chiu Lee",
      "sequence": 30,
      "roles": [],
      "notes": ""
    },
    {
      "person_imdb_id": "nm3370683",
      "name": "Shao-Hua Li",
      "sequence": 31,
      "roles": [],
      "notes": ""
    },
    {
      "person_imdb_id": "nm1796567",
      "name": "Shang-Yun Liang",
      "sequence": 32,
      "roles": [],
      "notes": ""
    },
    {
      "person_imdb_id": "nm0514905",
      "name": "Chia-Yung Liu",
      "sequence": 33,
      "roles": [],
      "notes": ""
    },
    {
      "person_imdb_id": "nm1269227",
      "name": "Kang Liu",
      "sequence": 34,
      "roles": [],
      "notes": ""
    },
    {
      "person_imdb_id": "nm1796608",
      "name": "Wai Lo",
      "sequence": 35,
      "roles": [],
      "notes": ""
    },
    {
      "person_imdb_id": "nm0518064",
      "name": "Cliff Lok",
      "sequence": 36,
      "roles": [
        "Clan member"
      ],
      "notes": ""
    },
    {
      "person_imdb_id": "nm3085023",
      "name": "Jen-Ching Mi",
      "sequence": 37,
      "roles": [],
      "notes": ""
    },
    {
      "person_imdb_id": "nm0787935",
      "name": "Kwai Shan",
      "sequence": 38,
      "roles": [],
      "notes": ""
    },
    {
      "person_imdb_id": "nm2728414",
      "name": "Bao Tan",
      "sequence": 39,
      "roles": [],
      "notes": ""
    },
    {
      "person_imdb_id": "nm4575850",
      "name": "Yung-Chieh Tan",
      "sequence": 40,
      "roles": [],
      "notes": ""
    },
    {
      "person_imdb_id": "nm0849271",
      "name": "Chia Tang",
      "sequence": 41,
      "roles": [],
      "notes": ""
    },
    {
      "person_imdb_id": "nm0874664",
      "name": "Yen-Tsan Tang",
      "sequence": 42,
      "roles": [
        "Hu Erh"
      ],
      "notes": ""
    },
    {
      "person_imdb_id": "nm1832825",
      "name": "Te-Chiang Teng",
      "sequence": 43,
      "roles": [],
      "notes": ""
    },
    {
      "person_imdb_id": "nm0875130",
      "name": "Chor-Lam Tsang",
      "sequence": 44,
      "roles": [],
      "notes": ""
    },
    {
      "person_imdb_id": "nm0437619",
      "name": "Li Tung",
      "sequence": 45,
      "roles": [
        "Ting of Lo Brothers"
      ],
      "notes": "(as Kang Hua)"
    },
    {
      "person_imdb_id": "nm2387260",
      "name": "Tsai-Pao Tung",
      "sequence": 46,
      "roles": [],
      "notes": ""
    },
    {
      "person_imdb_id": "nm0910869",
      "name": "Chung Wang",
      "sequence": 47,
      "roles": [
        "Fan Wu-ting"
      ],
      "notes": ""
    },
    {
      "person_imdb_id": "nm1560037",
      "name": "Kuang Yu Wang",
      "sequence": 48,
      "roles": [
        "Fang Sheng"
      ],
      "notes": ""
    },
    {
      "person_imdb_id": "nm0702666",
      "name": "Ching Wong",
      "sequence": 49,
      "roles": [],
      "notes": "(as Tsing Wang)"
    },
    {
      "person_imdb_id": "nm2389603",
      "name": "Mei Wong",
      "sequence": 50,
      "roles": [],
      "notes": ""
    },
    {
      "person_imdb_id": "nm0939327",
      "name": "Shu-Tong Wong",
      "sequence": 51,
      "roles": [],
      "notes": "(as Shu-Tang Huang)"
    },
    {
      "person_imdb_id": "nm3114260",
      "name": "Yuan-Shun Wu",
      "sequence": 52,
      "roles": [],
      "notes": ""
    },
    {
      "person_imdb_id": "nm0906219",
      "name": "Hua Yang",
      "sequence": 53,
      "roles": [],
      "notes": ""
    },
    {
      "person_imdb_id": "nm0945188",
      "name": "Shi-Kwan Yen",
      "sequence": 54,
      "roles": [],
      "notes": ""
    },
    {
      "person_imdb_id": "nm2403022",
      "name": "Leng-Kuang Yin",
      "sequence": 55,
      "roles": [],
      "notes": ""
    },
    {
      "person_imdb_id": "nm1533468",
      "name": "Lung Yu",
      "sequence": 56,
      "roles": [
        "Chu Hung"
      ],
      "notes": ""
    },
    {
      "person_imdb_id": "nm0950604",
      "name": "Cheung-Yan Yuen",
      "sequence": 57,
      "roles": [],
      "notes": "(as Hsiang-Jen Yuan)"
    },
    {
      "person_imdb_id": "nm5428344",
      "name": "Shing-Chau Yuen",
      "sequence": 58,
      "roles": [],
      "notes": ""
    },
    {
      "person_imdb_id": "nm0950751",
      "name": "Shun-Yee Yuen",
      "sequence": 59,
      "roles": [],
      "notes": ""
    },
    {
      "person_imdb_id": "nm0950759",
      "name": "Woo-Ping Yuen",
      "sequence": 60,
      "roles": [
        "Thug"
      ],
      "notes": ""
    }
  ],
  "writers": [
    {
      "person_imdb_id": "nm0393250",
      "name": "Kuang Ni",
      "group": 0,
      "sequence": 0,
      "notes": "() (as Kuang I)"
    }
  ],
  "release_date": "1971-01-01",
  "release_date_notes": "No release date",
  "countries": [
    "Hong Kong"
  ],
  "genres": [
    "Action",
    "Drama"
  ]
}