{
  "imdb_id": "tt0067328",
  "sort_title": "Last Picture Show (1971)",
  "performers": [
    {
      "movie_imdb_id": "tt0067328",
      "person_imdb_id": "nm0000961",
      "name": "Timothy Bottoms",
      "sequence": 0,
      "notes": "",
      "roles": [
        "Sonny Crawford"
      ]
    },
    {
      "movie_imdb_id": "tt0067328",
      "person_imdb_id": "nm0000313",
      "name": "Jeff Bridges",
      "sequence": 1,
      "notes": "",
      "roles": [
        "Duane Jackson"
      ]
    },
    {
      "movie_imdb_id": "tt0067328",
      "person_imdb_id": "nm0001732",
      "name": "Cybill Shepherd",
      "sequence": 2,
      "notes": "",
      "roles": [
        "Jacy Farrow"
      ]
    },
    {
      "movie_imdb_id": "tt0067328",
      "person_imdb_id": "nm0424565",
      "name": "Ben Johnson",
      "sequence": 3,
      "notes": "",
      "roles": [
        "Sam the Lion"
      ]
    },
    {
      "movie_imdb_id": "tt0067328",
      "person_imdb_id": "nm0001458",
      "name": "Cloris Leachman",
      "sequence": 4,
      "notes": "",
      "roles": [
        "Ruth Popper"
      ]
    },
    {
      "movie_imdb_id": "tt0067328",
      "person_imdb_id": "nm0000995",
      "name": "Ellen Burstyn",
      "sequence": 5,
      "notes": "",
      "roles": [
        "Lois Farrow"
      ]
    },
    {
      "movie_imdb_id": "tt0067328",
      "person_imdb_id": "nm0107281",
      "name": "Eileen Brennan",
      "sequence": 6,
      "notes": "",
      "roles": [
        "Genevieve"
      ]
    },
    {
      "movie_imdb_id": "tt0067328",
      "person_imdb_id": "nm0347656",
      "name": "Clu Gulager",
      "sequence": 7,
      "notes": "",
      "roles": [
        "Abilene"
      ]
    },
    {
      "movie_imdb_id": "tt0067328",
      "person_imdb_id": "nm0098734",
      "name": "Sam Bottoms",
      "sequence": 8,
      "notes": "",
      "roles": [
        "Billy"
      ]
    },
    {
      "movie_imdb_id": "tt0067328",
      "person_imdb_id": "nm0880580",
      "name": "Sharon Ullrick",
      "sequence": 9,
      "notes": "(as Sharon Taggart)",
      "roles": [
        "Charlene Duggs"
      ]
    },
    {
      "movie_imdb_id": "tt0067328",
      "person_imdb_id": "nm0001642",
      "name": "Randy Quaid",
      "sequence": 10,
      "notes": "",
      "roles": [
        "Lester Marlow"
      ]
    },
    {
      "movie_imdb_id": "tt0067328",
      "person_imdb_id": "nm0372723",
      "name": "Joe Heathcock",
      "sequence": 11,
      "notes": "",
      "roles": [
        "Sheriff"
      ]
    },
    {
      "movie_imdb_id": "tt0067328",
      "person_imdb_id": "nm0862174",
      "name": "Bill Thurman",
      "sequence": 12,
      "notes": "",
      "roles": [
        "Coach Popper"
      ]
    },
    {
      "movie_imdb_id": "tt0067328",
      "person_imdb_id": "nm0236281",
      "name": "Barc Doyle",
      "sequence": 13,
      "notes": "",
      "roles": [
        "Joe Bob Blanton"
      ]
    },
    {
      "movie_imdb_id": "tt0067328",
      "person_imdb_id": "nm0298479",
      "name": "Jessie Lee Fulton",
      "sequence": 14,
      "notes": "",
      "roles": [
        "Miss Mosey"
      ]
    },
    {
      "movie_imdb_id": "tt0067328",
      "person_imdb_id": "nm0110668",
      "name": "Gary Brockette",
      "sequence": 15,
      "notes": "",
      "roles": [
        "Bobby Sheen"
      ]
    },
    {
      "movie_imdb_id": "tt0067328",
      "person_imdb_id": "nm0401666",
      "name": "Helena Humann",
      "sequence": 16,
      "notes": "",
      "roles": [
        "Jimmie Sue"
      ]
    },
    {
      "movie_imdb_id": "tt0067328",
      "person_imdb_id": "nm0146178",
      "name": "Loyd Catlett",
      "sequence": 17,
      "notes": "",
      "roles": [
        "Leroy"
      ]
    },
    {
      "movie_imdb_id": "tt0067328",
      "person_imdb_id": "nm0322654",
      "name": "Robert Glenn",
      "sequence": 18,
      "notes": "",
      "roles": [
        "Gene Farrow"
      ]
    },
    {
      "movie_imdb_id": "tt0067328",
      "person_imdb_id": "nm0384916",
      "name": "John Hillerman",
      "sequence": 19,
      "notes": "",
      "roles": [
        "Teacher"
      ]
    },
    {
      "movie_imdb_id": "tt0067328",
      "person_imdb_id": "nm0641734",
      "name": "Janice E. O'Malley",
      "sequence": 20,
      "notes": "(as Janice O'Malley)",
      "roles": [
        "Mrs. Clarg"
      ]
    },
    {
      "movie_imdb_id": "tt0067328",
      "person_imdb_id": "nm0536760",
      "name": "Floyd Mahaney",
      "sequence": 21,
      "notes": "",
      "roles": [
        "Oklahoma Patrolman"
      ]
    },
    {
      "movie_imdb_id": "tt0067328",
      "person_imdb_id": "nm0404996",
      "name": "Kimberly Hyde",
      "sequence": 22,
      "notes": "",
      "roles": [
        "Annie Annie Martin"
      ]
    },
    {
      "movie_imdb_id": "tt0067328",
      "person_imdb_id": "nm0932244",
      "name": "Noble Willingham",
      "sequence": 23,
      "notes": "",
      "roles": [
        "Chester"
      ]
    },
    {
      "movie_imdb_id": "tt0067328",
      "person_imdb_id": "nm0419620",
      "name": "Marjorie Jay",
      "sequence": 24,
      "notes": "",
      "roles": [
        "Winnie Snips"
      ]
    },
    {
      "movie_imdb_id": "tt0067328",
      "person_imdb_id": "nm0368008",
      "name": "Joye Hash",
      "sequence": 25,
      "notes": "",
      "roles": [
        "Mrs. Jackson"
      ]
    },
    {
      "movie_imdb_id": "tt0067328",
      "person_imdb_id": "nm0445740",
      "name": "Pamela Keller",
      "sequence": 26,
      "notes": "",
      "roles": [
        "Jackie Lee French"
      ]
    },
    {
      "movie_imdb_id": "tt0067328",
      "person_imdb_id": "nm0403602",
      "name": "Gordon Hurst",
      "sequence": 27,
      "notes": "",
      "roles": [
        "Monroe"
      ]
    },
    {
      "movie_imdb_id": "tt0067328",
      "person_imdb_id": "nm0395936",
      "name": "Mike Hosford",
      "sequence": 28,
      "notes": "",
      "roles": [
        "Johnny"
      ]
    },
    {
      "movie_imdb_id": "tt0067328",
      "person_imdb_id": "nm0429942",
      "name": "Faye Jordan",
      "sequence": 29,
      "notes": "",
      "roles": [
        "Nurse"
      ]
    },
    {
      "movie_imdb_id": "tt0067328",
      "person_imdb_id": "nm0786713",
      "name": "Charles Seybert",
      "sequence": 30,
      "notes": "",
      "roles": [
        "Andy Fanner"
      ]
    },
    {
      "movie_imdb_id": "tt0067328",
      "person_imdb_id": "nm0507240",
      "name": "Grover Lewis",
      "sequence": 31,
      "notes": "",
      "roles": [
        "Mr. Crawford"
      ]
    },
    {
      "movie_imdb_id": "tt0067328",
      "person_imdb_id": "nm0880717",
      "name": "Rebecca Ulrick",
      "sequence": 32,
      "notes": "",
      "roles": [
        "Marlene"
      ]
    },
    {
      "movie_imdb_id": "tt0067328",
      "person_imdb_id": "nm0791830",
      "name": "Merrill Shepherd",
      "sequence": 33,
      "notes": "",
      "roles": [
        "Agnes"
      ]
    },
    {
      "movie_imdb_id": "tt0067328",
      "person_imdb_id": "nm0939592",
      "name": "Buddy Wood",
      "sequence": 34,
      "notes": "",
      "roles": [
        "Bud"
      ]
    },
    {
      "movie_imdb_id": "tt0067328",
      "person_imdb_id": "nm0939830",
      "name": "Kenny Wood",
      "sequence": 35,
      "notes": "",
      "roles": [
        "Ken"
      ]
    },
    {
      "movie_imdb_id": "tt0067328",
      "person_imdb_id": "nm0114086",
      "name": "Leon Brown",
      "sequence": 36,
      "notes": "",
      "roles": [
        "Cowboy in Cafe"
      ]
    },
    {
      "movie_imdb_id": "tt0067328",
      "person_imdb_id": "nm0570046",
      "name": "Bobby McGriff",
      "sequence": 37,
      "notes": "",
      "roles": [
        "Truck Driver"
      ]
    },
    {
      "movie_imdb_id": "tt0067328",
      "person_imdb_id": "nm0611060",
      "name": "Jack Mueller",
      "sequence": 38,
      "notes": "",
      "roles": [
        "Oil Pumper"
      ]
    },
    {
      "movie_imdb_id": "tt0067328",
      "person_imdb_id": "nm3306508",
      "name": "Robert Arnold",
      "sequence": 39,
      "notes": "",
      "roles": [
        "Brother Blanton"
      ]
    },
    {
      "movie_imdb_id": "tt0067328",
      "person_imdb_id": "nm0550881",
      "name": "Frank Marshall",
      "sequence": 40,
      "notes": "",
      "roles": [
        "Tommy Logan"
      ]
    },
    {
      "movie_imdb_id": "tt0067328",
      "person_imdb_id": "nm0553145",
      "name": "Tom Martin",
      "sequence": 41,
      "notes": "",
      "roles": [
        "Larry"
      ]
    },
    {
      "movie_imdb_id": "tt0067328",
      "person_imdb_id": "nm0255465",
      "name": "Otis Elmore",
      "sequence": 42,
      "notes": "",
      "roles": [
        "1st Mechanic"
      ]
    },
    {
      "movie_imdb_id": "tt0067328",
      "person_imdb_id": "nm1365854",
      "name": "Charles Salmon",
      "sequence": 43,
      "notes": "",
      "roles": [
        "Roughneck Driver"
      ]
    },
    {
      "movie_imdb_id": "tt0067328",
      "person_imdb_id": "nm0310068",
      "name": "George Gaulden",
      "sequence": 44,
      "notes": "",
      "roles": [
        "Cowboy"
      ]
    },
    {
      "movie_imdb_id": "tt0067328",
      "person_imdb_id": "nm0360456",
      "name": "Will Morris Hannis",
      "sequence": 45,
      "notes": "",
      "roles": [
        "Gas Station Man"
      ]
    },
    {
      "movie_imdb_id": "tt0067328",
      "person_imdb_id": "nm1385980",
      "name": "The Leon Miller Band",
      "sequence": 46,
      "notes": "",
      "roles": [
        "The Leon Miller Band"
      ]
    },
    {
      "movie_imdb_id": "tt0067328",
      "person_imdb_id": "nm0000953",
      "name": "Peter Bogdanovich",
      "sequence": 47,
      "notes": "(uncredited) (voice)",
      "roles": [
        "DJ"
      ]
    }
  ],
  "directors": [
    {
      "movie_imdb_id": "tt0067328",
      "person_imdb_id": "nm0000953",
      "name": "Peter Bogdanovich",
      "sequence": 0,
      "notes": ""
    }
  ],
  "writers": [
    {
      "movie_imdb_id": "tt0067328",
      "person_imdb_id": "nm0573505",
      "name": "Larry McMurtry",
      "sequence": 0,
      "notes": "(screenplay)",
      "group_id": 0
    },
    {
      "movie_imdb_id": "tt0067328",
      "person_imdb_id": "nm0000953",
      "name": "Peter Bogdanovich",
      "sequence": 0,
      "notes": "(screenplay)",
      "group_id": 0
    },
    {
      "movie_imdb_id": "tt0067328",
      "person_imdb_id": "nm0573505",
      "name": "Larry McMurtry",
      "sequence": 0,
      "notes": "(novel)",
      "group_id": 1
    }
  ],
  "release_date": "1971-10-02",
  "release_date_notes": "(New York Film Festival)"
}