{
  "imdb_id": "tt0098625",
  "sort_title": "We're No Angels (1989)",
  "performers": [
    {
      "person_imdb_id": "nm0000134",
      "name": "Robert De Niro",
      "sequence": 0,
      "notes": "",
      "roles": [
        "Ned"
      ]
    },
    {
      "person_imdb_id": "nm0000576",
      "name": "Sean Penn",
      "sequence": 1,
      "notes": "",
      "roles": [
        "Jim"
      ]
    },
    {
      "person_imdb_id": "nm0000193",
      "name": "Demi Moore",
      "sequence": 2,
      "notes": "",
      "roles": [
        "Molly"
      ]
    },
    {
      "person_imdb_id": "nm0001924",
      "name": "Hoyt Axton",
      "sequence": 3,
      "notes": "",
      "roles": [
        "Father Levesque"
      ]
    },
    {
      "person_imdb_id": "nm0456124",
      "name": "Bruno Kirby",
      "sequence": 4,
      "notes": "",
      "roles": [
        "Deputy"
      ]
    },
    {
      "person_imdb_id": "nm0564044",
      "name": "Ray McAnally",
      "sequence": 5,
      "notes": "",
      "roles": [
        "Warden"
      ]
    },
    {
      "person_imdb_id": "nm0751638",
      "name": "James Russo",
      "sequence": 6,
      "notes": "",
      "roles": [
        "Bobby"
      ]
    },
    {
      "person_imdb_id": "nm0001728",
      "name": "Wallace Shawn",
      "sequence": 7,
      "notes": "",
      "roles": [
        "Translator"
      ]
    },
    {
      "person_imdb_id": "nm0000604",
      "name": "John C. Reilly",
      "sequence": 8,
      "notes": "",
      "roles": [
        "Young Monk"
      ]
    },
    {
      "person_imdb_id": "nm0106319",
      "name": "Jay Brazeau",
      "sequence": 9,
      "notes": "",
      "roles": [
        "Sheriff"
      ]
    },
    {
      "person_imdb_id": "nm0119550",
      "name": "Ken Buhay",
      "sequence": 10,
      "notes": "",
      "roles": [
        "Bishop Nogalich"
      ]
    },
    {
      "person_imdb_id": "nm0492746",
      "name": "Elizabeth Lawrence",
      "sequence": 11,
      "notes": "",
      "roles": [
        "Mrs. Blair"
      ]
    },
    {
      "person_imdb_id": "nm2072312",
      "name": "Bill Murdoch",
      "sequence": 12,
      "notes": "",
      "roles": [
        "Deputy"
      ]
    },
    {
      "person_imdb_id": "nm0422674",
      "name": "Jessica Jickels",
      "sequence": 13,
      "notes": "",
      "roles": [
        "Rosie"
      ]
    },
    {
      "person_imdb_id": "nm0003964",
      "name": "Frank C. Turner",
      "sequence": 14,
      "notes": "",
      "roles": [
        "Shopkeeper"
      ]
    },
    {
      "person_imdb_id": "nm0908022",
      "name": "Matthew Walker",
      "sequence": 15,
      "notes": "",
      "roles": [
        "Blacksmith"
      ]
    },
    {
      "person_imdb_id": "nm0576324",
      "name": "Sheelah Megill",
      "sequence": 16,
      "notes": "",
      "roles": [
        "Townswoman"
      ]
    },
    {
      "person_imdb_id": "nm0398339",
      "name": "Sean Hoy",
      "sequence": 17,
      "notes": "",
      "roles": [
        "Workman"
      ]
    },
    {
      "person_imdb_id": "nm0077615",
      "name": "Lloyd Berry",
      "sequence": 18,
      "notes": "",
      "roles": [
        "Passersby"
      ]
    },
    {
      "person_imdb_id": "nm2012806",
      "name": "David McLeod",
      "sequence": 19,
      "notes": "",
      "roles": [
        "Passersby"
      ]
    },
    {
      "person_imdb_id": "nm0628236",
      "name": "Richard Newman",
      "sequence": 20,
      "notes": "",
      "roles": [
        "Passersby"
      ]
    },
    {
      "person_imdb_id": "nm0869378",
      "name": "Frank Totino",
      "sequence": 21,
      "notes": "",
      "roles": [
        "Bystander"
      ]
    },
    {
      "person_imdb_id": "nm0042439",
      "name": "Karen Elizabeth Austin",
      "sequence": 22,
      "notes": "(as Karen Austin)",
      "roles": [
        "Bystander"
      ]
    },
    {
      "person_imdb_id": "nm0390604",
      "name": "Antony Holland",
      "sequence": 23,
      "notes": "",
      "roles": [
        "Doctor"
      ]
    },
    {
      "person_imdb_id": "nm0218366",
      "name": "Sylvain Demers",
      "sequence": 24,
      "notes": "",
      "roles": [
        "Canadian Priest"
      ]
    },
    {
      "person_imdb_id": "nm0196748",
      "name": "Cory Dagg",
      "sequence": 25,
      "notes": "",
      "roles": [
        "Border Guard"
      ]
    },
    {
      "person_imdb_id": "nm0762560",
      "name": "Garwin Sanford",
      "sequence": 26,
      "notes": "",
      "roles": [
        "Prison Priest"
      ]
    },
    {
      "person_imdb_id": "nm0010101",
      "name": "Jack Ackroyd",
      "sequence": 27,
      "notes": "",
      "roles": [
        "Guard"
      ]
    },
    {
      "person_imdb_id": "nm0452308",
      "name": "James Kidnie",
      "sequence": 28,
      "notes": "",
      "roles": [
        "Guard"
      ]
    },
    {
      "person_imdb_id": "nm0063782",
      "name": "Gerry Bean",
      "sequence": 29,
      "notes": "",
      "roles": [
        "Guard"
      ]
    },
    {
      "person_imdb_id": "nm0689868",
      "name": "Rick Poltaruk",
      "sequence": 30,
      "notes": "",
      "roles": [
        "Fat Monk"
      ]
    }
  ],
  "directors": [
    {
      "person_imdb_id": "nm0001403",
      "name": "Neil Jordan",
      "sequence": 0,
      "notes": ""
    }
  ],
  "writers": [
    {
      "person_imdb_id": "nm0000519",
      "name": "David Mamet",
      "sequence": 0,
      "notes": "(written by)",
      "group_id": 0
    },
    {
      "person_imdb_id": "nm0532030",
      "name": "Ranald MacDougall",
      "sequence": 0,
      "notes": "(earlier screenplay) (suggestion) (as Ranald Macdougall)",
      "group_id": 1
    },
    {
      "person_imdb_id": "nm0404062",
      "name": "Albert Husson",
      "sequence": 0,
      "notes": "(play \"La Cuisine Des Anges\") (suggestion)",
      "group_id": 2
    },
    {
      "person_imdb_id": "nm0818416",
      "name": "Sam Spewack",
      "sequence": 0,
      "notes": "(play \"My Three Angels\") (suggestion)",
      "group_id": 3
    },
    {
      "person_imdb_id": "nm0818415",
      "name": "Bella Spewack",
      "sequence": 0,
      "notes": "(play \"My Three Angels\") (suggestion)",
      "group_id": 3
    }
  ],
  "release_date": "1989-12-15",
  "release_date_notes": "",
  "countries": [
    "United States"
  ]
}